urlmonitor/__init__.py
urlmonitor/actionbase.py
urlmonitor/minder.py
urlmonitor/nsdict.py
urlmonitor/webchecker.py
urlmonitor/actions/__init__.py
urlmonitor/actions/email_notify.py
urlmonitor/actions/re_match.py
urlmonitor/actions/run_script.py
urlmonitor-0.0.9.dist-info/LICENSE
urlmonitor-0.0.9.dist-info/METADATA
urlmonitor-0.0.9.dist-info/WHEEL
urlmonitor-0.0.9.dist-info/entry_points.txt
urlmonitor-0.0.9.dist-info/top_level.txt
urlmonitor-0.0.9.dist-info/RECORD
