Metadata-Version: 2.1
Name: urlmonitor
Version: 0.0.9
Summary: Check url and run actions if changed
Home-page: https://github.com/destrangis/urlmonitor
Author: Javier Llopis
Author-email: javier@llopis.me
License: UNKNOWN
Platform: UNKNOWN
Classifier: Development Status :: 4 - Beta
Classifier: Environment :: Console
Classifier: Intended Audience :: End Users/Desktop
Classifier: Intended Audience :: System Administrators
Classifier: License :: OSI Approved :: MIT License
Classifier: Operating System :: OS Independent
Classifier: Programming Language :: Python :: 3.7
Classifier: Topic :: Internet
Classifier: Topic :: Office/Business
Classifier: Topic :: System
Classifier: Topic :: System :: Monitoring
Classifier: Topic :: System :: Networking :: Monitoring
Classifier: Topic :: Utilities
Requires-Dist: PyYAML (>=5.1)
Requires-Dist: requests (>=2.21)
